LICENSE.txt
MANIFEST.in
README.md
requirements.txt
setup.py
cachey/__init__.py
cachey/cache.py
cachey/nbytes.py
cachey/score.py
cachey.egg-info/PKG-INFO
cachey.egg-info/SOURCES.txt
cachey.egg-info/dependency_links.txt
cachey.egg-info/not-zip-safe
cachey.egg-info/requires.txt
cachey.egg-info/top_level.txt
cachey/tests/test_cache.py
cachey/tests/test_nbytes.py
cachey/tests/test_score.py