Metadata-Version: 1.0
Name: cachey
Version: 0.1.1
Summary: Caching mindful of computation/storage costs
Home-page: http://github.com/mrocklin/cachey/
Author: Matthew Rocklin
Author-email: mrocklin@gmail.com
License: BSD
Platform: UNKNOWN
